BgoKit/ToolKit.py
BgoKit/__init__.py
bgokit-0.1.0.dist-info/METADATA
bgokit-0.1.0.dist-info/WHEEL
bgokit-0.1.0.dist-info/top_level.txt
bgokit-0.1.0.dist-info/RECORD
