Metadata-Version: 2.4
Name: BgoKit
Version: 0.1.0
Summary: A tool package for Bgolearn
Home-page: https://github.com/Bin-Cao/Bgolearn
Author: CaoBin
Author-email: binjacobcao@gmail.com
Maintainer: CaoBin
Maintainer-email: binjacobcao@gmail.com
License: MIT License
Classifier: Development Status :: 3 - Alpha
Classifier: Intended Audience :: Developers
Classifier: Topic :: Software Development :: Build Tools
Classifier: License :: OSI Approved :: MIT License
Classifier: Programming Language :: Python :: 3
Requires-Python: >=3.7
Requires-Dist: numpy
Requires-Dist: matplotlib
Dynamic: author
Dynamic: author-email
Dynamic: classifier
Dynamic: description
Dynamic: home-page
Dynamic: license
Dynamic: maintainer
Dynamic: maintainer-email
Dynamic: requires-dist
Dynamic: requires-python
Dynamic: summary
